dustmaps3d/__init__.py
dustmaps3d/core.py
dustmaps3d-2.2.11.dist-info/licenses/LICENSE
dustmaps3d-2.2.11.dist-info/METADATA
dustmaps3d-2.2.11.dist-info/WHEEL
dustmaps3d-2.2.11.dist-info/top_level.txt
dustmaps3d-2.2.11.dist-info/RECORD
