Metadata-Version: 2.4
Name: dustmaps3d
Version: 2.2.11
Summary: An all-sky 3D dust map based on Gaia and LAMOST.
Author-email: Wang Tao <wt@mail.bnu.edu.cn>
License: MIT
Project-URL: Homepage, https://github.com/Grapeknight/dustmaps3d
Classifier: Development Status :: 5 - Production/Stable
Classifier: Intended Audience :: Science/Research
Classifier: License :: OSI Approved :: MIT License
Classifier: Programming Language :: Python :: 3
Classifier: Operating System :: OS Independent
Classifier: Topic :: Scientific/Engineering :: Astronomy
Requires-Python: >=3.7.1
License-File: LICENSE
Requires-Dist: numpy
Requires-Dist: pandas
Requires-Dist: astropy
Requires-Dist: astropy-healpix
Requires-Dist: tqdm
Requires-Dist: platformdirs
Requires-Dist: requests
Dynamic: license-file
